codemodder/__init__.py
codemodder/_version.py
codemodder/cli.py
codemodder/code_directory.py
codemodder/codemodder.py
codemodder/codeql.py
codemodder/context.py
codemodder/dependency.py
codemodder/diff.py
codemodder/file_context.py
codemodder/llm.py
codemodder/logging.py
codemodder/providers.py
codemodder/registry.py
codemodder/result.py
codemodder/sarifs.py
codemodder/semgrep.py
codemodder/codemods/__init__.py
codemodder/codemods/api.py
codemodder/codemods/base_codemod.py
codemodder/codemods/base_detector.py
codemodder/codemods/base_transformer.py
codemodder/codemods/base_visitor.py
codemodder/codemods/check_annotations.py
codemodder/codemods/codeql.py
codemodder/codemods/import_modifier_codemod.py
codemodder/codemods/imported_call_modifier.py
codemodder/codemods/libcst_transformer.py
codemodder/codemods/regex_transformer.py
codemodder/codemods/semgrep.py
codemodder/codemods/utils.py
codemodder/codemods/utils_mixin.py
codemodder/codemods/xml_transformer.py
codemodder/codemods/test/__init__.py
codemodder/codemods/test/integration_utils.py
codemodder/codemods/test/utils.py
codemodder/codemods/test/validations.py
codemodder/codemods/transformations/__init__.py
codemodder/codemods/transformations/clean_imports.py
codemodder/codemods/transformations/remove_empty_string_concatenation.py
codemodder/codemods/transformations/remove_unused_imports.py
codemodder/codetf/__init__.py
codemodder/codetf/common.py
codemodder/codetf/v2/codetf.py
codemodder/codetf/v3/codetf.py
codemodder/dependency_management/__init__.py
codemodder/dependency_management/base_dependency_writer.py
codemodder/dependency_management/dependency_manager.py
codemodder/dependency_management/pyproject_writer.py
codemodder/dependency_management/requirements_txt_writer.py
codemodder/dependency_management/setup_py_writer.py
codemodder/dependency_management/setupcfg_writer.py
codemodder/project_analysis/__init__.py
codemodder/project_analysis/python_repo_manager.py
codemodder-6.5.5.dist-info/licenses/LICENSE
codemodder-6.5.5.dist-info/METADATA
codemodder-6.5.5.dist-info/WHEEL
codemodder-6.5.5.dist-info/entry_points.txt
codemodder-6.5.5.dist-info/top_level.txt
codemodder-6.5.5.dist-info/RECORD
