Metadata-Version: 2.4
Name: codemodder
Version: 6.5.5
Summary: A pluggable framework for building codemods in Python
Author-email: Pixee <python@pixee.ai>
License:                     GNU AFFERO GENERAL PUBLIC LICENSE
Project-URL: Homepage, https://codemodder.io
Project-URL: Repository, https://github.com/pixee/codemodder-python
Keywords: codemod,codemods,security,fix,fixes
Classifier: Development Status :: 4 - Beta
Classifier: Intended Audience :: Developers
Classifier: License :: OSI Approved :: GNU Affero General Public License v3
Classifier: Programming Language :: Python :: 3.14
Classifier: Programming Language :: Python :: 3.13
Classifier: Programming Language :: Python :: 3.12
Classifier: Programming Language :: Python :: 3.11
Classifier: Programming Language :: Python :: 3.10
Classifier: Topic :: Software Development
Classifier: Topic :: Security
Requires-Python: >=3.10.0
License-File: LICENSE
Requires-Dist: boltons<25.1,>=21.0
Requires-Dist: GitPython<4
Requires-Dist: isort<7,>=6.1
Requires-Dist: libcst<1.9,>=1.8
Requires-Dist: packaging<25.1,>=24.2
Requires-Dist: pydantic~=2.12.3
Requires-Dist: pylint<4.1,>=4
Requires-Dist: python-json-logger~=4.0.0
Requires-Dist: PyYAML~=6.0.0
Requires-Dist: toml~=0.10.2
Requires-Dist: tomlkit~=0.13.0
Requires-Dist: wrapt~=1.17.0
Requires-Dist: chardet~=5.2.0
Requires-Dist: sarif-pydantic~=0.6.1
Requires-Dist: setuptools~=80.0
Provides-Extra: semgrep
Requires-Dist: semgrep<1.141,>=1.140; extra == "semgrep"
Provides-Extra: test
Requires-Dist: azure-ai-inference<2.0,>=1.0.0b1; extra == "test"
Requires-Dist: coverage<7.12,>=7.11; extra == "test"
Requires-Dist: coverage-threshold~=0.4; extra == "test"
Requires-Dist: defusedxml==0.7.1; extra == "test"
Requires-Dist: types-defusedxml==0.7.0.20250822; extra == "test"
Requires-Dist: flask-wtf==1.2.2; extra == "test"
Requires-Dist: types-WTForms==3.2.1.20250809; extra == "test"
Requires-Dist: Flask<4; extra == "test"
Requires-Dist: httpx~=0.27; extra == "test"
Requires-Dist: Jinja2~=3.1.2; extra == "test"
Requires-Dist: jsonschema~=4.25.0; extra == "test"
Requires-Dist: lxml<6.1.0,>=6.0.0; extra == "test"
Requires-Dist: openai<1.110,>=1.109; extra == "test"
Requires-Dist: mock==5.2.*; extra == "test"
Requires-Dist: pre-commit<5; extra == "test"
Requires-Dist: Pyjwt~=2.10.0; extra == "test"
Requires-Dist: pytest<9,>=8.2; extra == "test"
Requires-Dist: pytest-asyncio~=1.0; extra == "test"
Requires-Dist: pytest-cov<8,>=7; extra == "test"
Requires-Dist: pytest-mock<3.16,>=3.15; extra == "test"
Requires-Dist: pytest-randomly==4.*; extra == "test"
Requires-Dist: pytest-xdist==3.*; extra == "test"
Requires-Dist: requests~=2.32.1; extra == "test"
Requires-Dist: security==1.3.1; extra == "test"
Requires-Dist: types-mock==5.2.*; extra == "test"
Requires-Dist: django<6,>=4; extra == "test"
Requires-Dist: numpy==2.2.6; python_version == "3.10" and extra == "test"
Requires-Dist: numpy~=2.3.0; python_version > "3.10" and extra == "test"
Requires-Dist: flask_wtf~=1.2.0; extra == "test"
Requires-Dist: fickling>=0.1.3,~=0.1.0; extra == "test"
Requires-Dist: graphql-server~=3.0.0b9; extra == "test"
Requires-Dist: unidiff>=0.7.5; extra == "test"
Requires-Dist: semgrep<1.141,>=1.140; extra == "test"
Provides-Extra: complexity
Requires-Dist: radon==6.0.*; extra == "complexity"
Requires-Dist: xenon==0.9.*; extra == "complexity"
Provides-Extra: openai
Requires-Dist: openai<1.110,>=1.109; extra == "openai"
Provides-Extra: azure
Requires-Dist: azure-ai-inference<2.0,>=1.0.0b1; extra == "azure"
Provides-Extra: all
Requires-Dist: codemodder[test]; extra == "all"
Requires-Dist: codemodder[complexity]; extra == "all"
Dynamic: license-file
